Metadata-Version: 2.1
Name: djangocms-page-meta-maykin
Version: 1.5.0.dev1
Summary: OpenGraph, Twitter Card and Schema.org snippet tags for django CMS 3 pages
Home-page: https://github.com/nephila/djangocms-page-meta
Author: Iacopo Spalletti
Author-email: i.spalletti@nephila.digital
License: BSD
Project-URL: Documentation, https://djangocms-page-meta.readthedocs.io/
Keywords: django cms,meta tags,OpenGraph,Twitter Cards,Schema.org,django-app-enabler addon
Classifier: Development Status :: 5 - Production/Stable
Classifier: Framework :: Django
Classifier: Intended Audience :: Developers
Classifier: License :: OSI Approved :: BSD License
Classifier: Natural Language :: English
Classifier: Framework :: Django
Classifier: Framework :: Django :: 3.2
Classifier: Framework :: Django :: 4.1
Classifier: Framework :: Django :: 4.2
Classifier: Programming Language :: Python :: 3
Classifier: Programming Language :: Python :: 3.9
Classifier: Programming Language :: Python :: 3.10
Classifier: Programming Language :: Python :: 3.11
Requires-Python: >=3.9
License-File: LICENSE
Requires-Dist: django-cms~=4.1
Requires-Dist: django-meta>=2.4.0
Requires-Dist: django-filer>=3.0
Provides-Extra: docs
Requires-Dist: django<5.0; extra == "docs"
Requires-Dist: sphinx<6,>2; extra == "docs"
Requires-Dist: djangocms-page-tags; extra == "docs"
